AUTHORS.txt
CHANGELOG.rst
LICENSE
MANIFEST.in
README.md
setup.py
xpdconf/__init__.py
xpdconf/conf.py
xpdconf.egg-info/PKG-INFO
xpdconf.egg-info/SOURCES.txt
xpdconf.egg-info/dependency_links.txt
xpdconf.egg-info/not-zip-safe
xpdconf.egg-info/top_level.txt
xpdconf/examples/pdf.yaml
xpdconf/examples/sim.yaml
xpdconf/examples/sim_db.yaml
xpdconf/examples/xpd.yaml
xpdconf/tests/__init__.py
xpdconf/tests/test_base_dir.py
xpdconf/tests/test_conf.py
xpdconf/tests/test_loadyaml.py