Metadata-Version: 1.0
Name: xpdconf
Version: 0.4.5
Summary: data processing module
Home-page: https://github.com/xpdAcq/xpdConf
Author: UNKNOWN
Author-email: UNKNOWN
License: UNKNOWN
Platform: UNKNOWN
